MANIFEST.in
setup.py
django_cssjspacker/.DS_Store
django_cssjspacker/__init__.py
django_cssjspacker/models.py
django_cssjspacker/tests.py
django_cssjspacker/views.py
django_cssjspacker/yuicompressor-2.4.2.jar
django_cssjspacker.egg-info/PKG-INFO
django_cssjspacker.egg-info/SOURCES.txt
django_cssjspacker.egg-info/dependency_links.txt
django_cssjspacker.egg-info/not-zip-safe
django_cssjspacker.egg-info/top_level.txt
django_cssjspacker/templatetags/.DS_Store
django_cssjspacker/templatetags/__init__.py
django_cssjspacker/templatetags/yui.py