Metadata-Version: 1.0
Name: django-cssjspacker
Version: 0.2
Summary: django application for js and css compression
Home-page: http://bitbucket.org/n0s/django-cssjspacker/wiki/
Author: n0s
Author-email: me@n0s.name
License: BSD
Keywords: django
Platform: UNKNOWN
